arrange_videochat/__init__.py
arrange_videochat/admin.py
arrange_videochat/apps.py
arrange_videochat/forms.py
arrange_videochat/middleware.py
arrange_videochat/models.py
arrange_videochat/translation.py
arrange_videochat/urls.py
arrange_videochat/views.py
arrange_videochat/migrations/0001_initial.py
arrange_videochat/migrations/__init__.py
arrange_videochat/templates/base.html
arrange_videochat/templates/arrange_videochat/_event.html
arrange_videochat/templates/arrange_videochat/_terms_modal.html
arrange_videochat/templates/arrange_videochat/event_confirm_delete.html
arrange_videochat/templates/arrange_videochat/full_or_past.html
arrange_videochat/templates/arrange_videochat/host.html
arrange_videochat/templates/arrange_videochat/hosted.html
arrange_videochat/templates/arrange_videochat/list.html
arrange_videochat/templates/arrange_videochat/participate.html
arrange_videochat/templates/arrange_videochat/participated.html
arrange_videochat/templates/arrange_videochat/participation_confirm_delete.html
arrange_videochat/tests/__init__.py
arrange_videochat/tests/test_commands.py
arrange_videochat/tests/test_models.py
arrange_videochat/tests/test_views.py
arrange_videochat-0.1.1.dist-info/LICENSE
arrange_videochat-0.1.1.dist-info/METADATA
arrange_videochat-0.1.1.dist-info/WHEEL
arrange_videochat-0.1.1.dist-info/top_level.txt
arrange_videochat-0.1.1.dist-info/RECORD
