Metadata-Version: 2.1
Name: arrange-videochat
Version: 0.1.1
Summary: A Django app to arrange a meeting for a video chat
Home-page: https://github.com/CoronaCircles/arrange_videochat
Author: Henrik Kröger
Author-email: hedwig@riseup.net
License: MIT
Platform: UNKNOWN
Classifier: Environment :: Web Environment
Classifier: Framework :: Django
Classifier: Framework :: Django :: 3.0
Classifier: Intended Audience :: Developers
Classifier: License :: OSI Approved :: MIT License
Classifier: Operating System :: OS Independent
Classifier: Programming Language :: Python
Classifier: Programming Language :: Python :: 3
Classifier: Programming Language :: Python :: 3 :: Only
Classifier: Programming Language :: Python :: 3.6
Classifier: Programming Language :: Python :: 3.7
Classifier: Programming Language :: Python :: 3.8
Classifier: Topic :: Internet :: WWW/HTTP
Classifier: Topic :: Internet :: WWW/HTTP :: Dynamic Content
Requires-Dist: django-crispy-forms
Requires-Dist: django-bootstrap-datepicker-plus
Requires-Dist: icalendar
Requires-Dist: django-modeltranslation
